{
  "cli": {
    "version": ">= 14.2.0"
  },
  "build": {
    "development": {
      "developmentClient": true,
      "distribution": "internal",
      "ios": {
        "resourceClass": "m-medium"
      },
      "env": {
        "APP_ENV": "development"
      }
    },
    "preview": {
      "distribution": "internal",
      "ios": {
        "resourceClass": "m-medium"
      },
      "env": {
        "APP_ENV": "production"
      }
    },
    "production": {
      "ios": {
        "resourceClass": "m-medium"
      },
      "env": {
        "APP_ENV": "production"
      }
    }
  }
}
